mytest7862/__init__.py
mytest7862-0.0.0.dist-info/DESCRIPTION.rst
mytest7862-0.0.0.dist-info/METADATA
mytest7862-0.0.0.dist-info/RECORD
mytest7862-0.0.0.dist-info/WHEEL
mytest7862-0.0.0.dist-info/metadata.json
mytest7862-0.0.0.dist-info/top_level.txt
