Metadata-Version: 2.0
Name: mytest7862
Version: 0.0.0
Summary: my test 7862
Home-page: https://github.com/gift-surg/mytest7862
Author: mytest7862 contributors
Author-email: UNKNOWN
License: UNKNOWN
Platform: UNKNOWN
